Metadata-Version: 2.1
Name: Flask-OneID
Version: 1.0.1
Summary: OneID integration with Flask application, (only for Uzbekistan)
Home-page: https://github.com/Odya-LLC/flask_oneid
Author: odya
Author-email: support@odya.uz
License: MIT
Platform: any
Classifier: Environment :: Web Environment
Classifier: Intended Audience :: Developers
Classifier: License :: OSI Approved :: MIT License
Classifier: Operating System :: OS Independent
Classifier: Programming Language :: Python
Classifier: Topic :: Internet :: WWW/HTTP :: Dynamic Content
Classifier: Topic :: Software Development :: Libraries :: Python Modules
